Metadata-Version: 1.0
Name: codestyle
Version: 0.3.5
Summary: Extendable codestyle checker and fixer
Home-page: https://github.com/webpp-studio/codestyle
Author: Sergey Levitin
Author-email: selevit@gmail.com
License: GPL licence, see LICENCE
Platform: UNKNOWN
